chatinpylib/__init__.py
chatinpylib/chat.py
chatinpylib/client.py
cmatlib-0.1.1.dist-info/METADATA
cmatlib-0.1.1.dist-info/WHEEL
cmatlib-0.1.1.dist-info/top_level.txt
cmatlib-0.1.1.dist-info/RECORD
