Metadata-Version: 2.4
Name: cmatlib
Version: 0.1.1
Summary: Синхронная библиотека для работы с ChatGPT с историей сессии
Author: Toqrul
Requires-Dist: openai>=1.0.0
